jafri_chromedriver_installer/__init__.py
jafri_chromedriver_installer/installer.py
jafri_chromedriver_installer-0.1.1.dist-info/LICENSE
jafri_chromedriver_installer-0.1.1.dist-info/METADATA
jafri_chromedriver_installer-0.1.1.dist-info/WHEEL
jafri_chromedriver_installer-0.1.1.dist-info/entry_points.txt
jafri_chromedriver_installer-0.1.1.dist-info/top_level.txt
jafri_chromedriver_installer-0.1.1.dist-info/RECORD
