Metadata-Version: 2.1
Name: jafri-chromedriver-installer
Version: 0.1.1
Summary: A package to automatically update Chromedriver to match the installed Chrome version.
Home-page: https://github.com/musharrafjafri/jafri-chromedriver-installer
Author: Musharraf Jafri
Author-email: musharrafsoft@gmail.com
Classifier: Programming Language :: Python :: 3
Classifier: License :: OSI Approved :: MIT License
Classifier: Operating System :: OS Independent
License-File: LICENSE
Requires-Dist: requests
